thriftpyi/__init__.py
thriftpyi/__main__.py
thriftpyi/cli.py
thriftpyi/entities.py
thriftpyi/files.py
thriftpyi/main.py
thriftpyi/proxies.py
thriftpyi/py.typed
thriftpyi/stubs.py
thriftpyi/utils.py
thrift_pyi-2.3.0.dist-info/METADATA
thrift_pyi-2.3.0.dist-info/WHEEL
thrift_pyi-2.3.0.dist-info/entry_points.txt
thrift_pyi-2.3.0.dist-info/licenses/AUTHORS.rst
thrift_pyi-2.3.0.dist-info/licenses/LICENSE
thrift_pyi-2.3.0.dist-info/RECORD
