Metadata-Version: 2.4
Name: thrift-pyi
Version: 2.3.0
Summary: This is simple `.pyi` stubs generator from thrift interfaces
License: MIT
License-File: AUTHORS.rst
License-File: LICENSE
Author: Aleksei Maslakov
Author-email: lesha.maslakov@gmail.com
Requires-Python: >=3.9,<4.0
Classifier: License :: OSI Approved :: MIT License
Classifier: Operating System :: OS Independent
Classifier: Programming Language :: Python :: 3
Classifier: Programming Language :: Python :: 3.9
Classifier: Programming Language :: Python :: 3.10
Classifier: Programming Language :: Python :: 3.11
Classifier: Programming Language :: Python :: 3.12
Classifier: Programming Language :: Python :: 3.13
Classifier: Programming Language :: Python :: 3.14
Classifier: Topic :: Software Development :: Code Generators
Requires-Dist: autoflake
Requires-Dist: black
Requires-Dist: thriftpy2 (>=0.4.2,<0.5.0)
Project-URL: Repository, https://github.com/unmade/thrift-pyi
